{"id":2172,"name":"Pubbliciter 4","language":"fr","user_id":130534,"username":"Ubriz","note":2.41,"votes":14,"scenes":["oy6%3A_checky28%3A%252Fuser%252Fcheck%253Fid%253DCI6yay6%3A_debugy37%3A%252Ftools%252FdebugFight%253Fsk%253DRJuhkynWy8%3A_mbottomi20y7%3A_mrightzy6%3A_equipy68%3Ahttp%253A%252F%252Fdata.dinorpg.com%252Fimg%252Ficons%252Fobj_%253A%253Aid%253A%253A.gify6%3A_sdinoy56%3Ahttp%253A%252F%252Fdata.dinorpg.com%252Fswf%252Fsdino.swf%253Fv%253D33y5%3A_dinoy55%3Ahttp%253A%252F%252Fdata.dinorpg.com%252Fswf%252Fdino.swf%253Fv%253D35y5%3A_dojony5%3A_mtopi130y3%3A_bgy57%3Ahttp%253A%252F%252Fdata.dinorpg.com%252Fimg%252Ffight%252Fs_totem.jpgy7%3A_groundy4%3Adirty8%3A_debriefy28%3Ajavascript%253AnextScene%2528%2529y8%3A_historylwy8%3A_Historyy9%3A_HDisplay%3A1nwR21y5%3A_HAdd%3A2oy6%3A_propsawy9%3A_Propertyy8%3A_PStatic%3A0hR10ty5%3A_lifei240y5%3A_namey3%3Aoliy5%3A_sidety5%3A_sizei240y4%3A_fidi1y4%3A_gfxy16%3A89vTGseWbYSqj000gnwR21R23%3A2oR24awR25R26%3A0hR10tR27i130R28y7%3AroscadeR30fR31i130R32i2R33y16%3A59Y90gG4Vl5S4000gnwR21y6%3A_HTalk%3A2i1y27%3Atu%2520est%2520trop%2520faible%2521wR21y10%3A_HAnnounce%3A2i2y9%3ATricheriewR21y7%3A_HRegen%3A3i2i500wy11%3A_LifeEffecty8%3A_LNormal%3A0wR21R39%3A2i1y11%3AAnti-trichewR21y6%3A_HLost%3A3i2i900wR42R43%3A0wR21y6%3A_HDead%3A1i2wR21y6%3A_HText%3A1y29%3ASoutener%2520l%2527anti-triche%2521wR21y8%3A_HFinish%3A2wy13%3A_EndBehavioury8%3A_EBStand%3A0wR50R51%3A0hy9%3A_smonstery59%3Ahttp%253A%252F%252Fdata.dinorpg.com%252Fswf%252Fsmonster.swf%253Fv%253D26g"]}