{"id":103813,"username":"siegsanskrie","language":"fr","inscription":"02 janvier 2008","rank":6891,"points":481,"dinoz":[{"name":"basset artesien","level":31,"data":"4943P1L6ZPe5l000"},{"name":"nono","level":31,"data":"89oaiQaYUfZGB000"},{"name":"megacephale","level":31,"data":"19bdWsYCVCcGj000"},{"name":"club","level":28,"data":"29MBJ0jNax09H000"},{"name":"orage","level":28,"data":"794B3QffKlE3F000"},{"name":"albinos","level":31,"data":"A90YHA397IIOX000"},{"name":"pattejaune","level":28,"data":"B9NuawICqjalf000"},{"name":"ulysse","level":26,"data":"894LQy0e5pFaM000"},{"name":"delta","level":26,"data":"39NLichjRCXpM000"},{"name":"comique","level":26,"data":"09JiVwOq5btP1000"},{"name":"chameau","level":27,"data":"99qHOGGerJHqE000"},{"name":"tamanoir","level":26,"data":"994gIZn6Ys9mu000"},{"name":"vautour","level":26,"data":"6972PfB3e3RkA000"},{"name":"totem","level":27,"data":"59LuTc4DuQwmv000"},{"name":"bleuet","level":22,"data":"99YTaxxpoKUyq000"},{"name":"badgorilla","level":23,"data":"A9TBSlknMRn9k000"},{"name":"dactylo","level":18,"data":"69tSrK29403tC000"},{"name":"lippu","level":19,"data":"59sba8Gu7kuxV000"},{"name":"largo","level":7,"data":"26JU8plcAf9pM000"}]}