{"id":16791,"username":"Shoren","language":"fr","inscription":"13 novembre 2007","rank":18580,"points":236,"dinoz":[{"name":"Shinai","level":22,"data":"89yA9JJWFXuBE000"},{"name":"Kso","level":22,"data":"39Wr1BK0EikkS000"},{"name":"Masaka","level":22,"data":"A9Qed26t3s8rP000"},{"name":"Slash","level":23,"data":"19gyzHz5Dlpwr000"},{"name":"Rorro","level":23,"data":"29t2jFuYjjL3o000"},{"name":"Pardito","level":23,"data":"B9FYFvfwn1IoC000"},{"name":"Winnie","level":21,"data":"69mfgBos2cvpt000"},{"name":"Chache","level":14,"data":"094NmD6sMJQyr000"},{"name":"Rubenstiger","level":14,"data":"79mGjiDNXks6t000"},{"name":"Bro","level":14,"data":"A9d9DJNbfUW7I000"},{"name":"Mermaillo","level":14,"data":"89ztgVOh8xFZ6000"},{"name":"Nessy","level":12,"data":"99iPy1YFpzvTk000"},{"name":"Marmol","level":12,"data":"59c4Bk10Ctfpk000"}]}