{"id":192922,"username":"iPoDAngel","language":"fr","inscription":"06 avril 2008","rank":4534,"points":604,"dinoz":[{"name":"Zehbi","level":44,"data":"09HKbapLzs5rc000"},{"name":"SirHeing","level":44,"data":"89mwuqvI2wMN0000"},{"name":"Hippoblou","level":44,"data":"996TXdqnbWxQn000"},{"name":"pterblu","level":44,"data":"69Hp4QlYFvb7u000"},{"name":"Grocky","level":30,"data":"594jrozXQMWnb000"},{"name":"Paugo","level":44,"data":"A9XssKjX5l7yX000"},{"name":"ripjizouss","level":31,"data":"59SUw7PxYlpI2000"},{"name":"Gobruni","level":28,"data":"A9WzqutLdKGsC000"},{"name":"Kabukake","level":28,"data":"E9DG61eJdNrhT000"},{"name":"Demon-Wan","level":47,"data":"BAjP0mrn9IVxm000"},{"name":"GORDEMONFROY","level":47,"data":"AAJvuMrNtevfc000"},{"name":"WAMON","level":47,"data":"BAnBkZ6Lu3eqK000"},{"name":"collecteur air","level":31,"data":"790gdLwjbrBLZ000"},{"name":"winksmon","level":10,"data":"2ApyfvJqL52Yc000"},{"name":"BortSAMPSON","level":31,"data":"19dgzyyWS1TF9000"},{"name":"BLOUPILL","level":31,"data":"29DRltL9Pdop8000"},{"name":"ROUSFOUF","level":1,"data":"H0hirjqOdLudq000"},{"name":"sacri","level":8,"data":"97OsaiQShPgpQ000"},{"name":"sacrife","level":7,"data":"B6LU2Z3QWGCZ6000"},{"name":"sacrifess","level":7,"data":"06f7BKx1EkZut000"}]}