{"id":351362,"username":"alice81","language":"fr","inscription":"21 juillet 2008","rank":9479,"points":395,"dinoz":[{"name":"singus","level":29,"data":"A9rtLN0qSrITu000"},{"name":"kitsou","level":28,"data":"89ZEmknfcjAAQ000"},{"name":"max","level":28,"data":"49pYIQbOqxhB5000"},{"name":"samy","level":28,"data":"09KYK8PT6kthl000"},{"name":"rick","level":28,"data":"B9a7xw7jCqcUV000"},{"name":"aby","level":27,"data":"59OryLGQCZmIH000"},{"name":"bubulle","level":28,"data":"79IX5dYpKQkHP000"},{"name":"wynx","level":28,"data":"29jZ757nToqnU000"},{"name":"Shiva","level":28,"data":"69UFvfGne6S9P000"},{"name":"Lipou","level":27,"data":"99a8O6C640sju000"},{"name":"brock","level":26,"data":"192XYTNw9zqen000"},{"name":"BibiLolo","level":24,"data":"39JKRA8MHhFOM000"},{"name":"KingKong","level":22,"data":"A94nC31ERQp4a000"},{"name":"Pika","level":22,"data":"B9Dty6EGx6m09000"},{"name":"Casper","level":22,"data":"39AVCrxmzrVJa000"}]}