{"id":42306,"username":"zaraben","language":"fr","inscription":"22 novembre 2007","rank":11378,"points":348,"dinoz":[{"name":"Araz","level":27,"data":"B9XvVwt1Ew8NF000"},{"name":"Furax","level":25,"data":"19zUZoDnV8PXC000"},{"name":"Moutaniche","level":25,"data":"49dB2l5vTDsrp000"},{"name":"Rex","level":19,"data":"890uXBDwcN0dM000"},{"name":"SpychoWhite","level":19,"data":"8931OqAqrIASd000"},{"name":"Poux Cornu","level":19,"data":"299z8fdSet6QV000"},{"name":"Rennino","level":18,"data":"C9u3yskocySP6000"},{"name":"PrisonBreak","level":18,"data":"09UNPbJCOFujB000"},{"name":"Oook Oook","level":18,"data":"A9kIKd7ibjffZ000"},{"name":"Noraye","level":19,"data":"39kHIypBULfPQ000"},{"name":"Standard","level":19,"data":"795ZxsquJfYp8000"},{"name":"Phoenix","level":18,"data":"69EZVXlW0cJYJ000"},{"name":"Hulky","level":18,"data":"99zonr5XXhkBO000"},{"name":"Ptit Bleu","level":18,"data":"99gSFkuNR769z000"},{"name":"Bananachoco","level":17,"data":"A9OSrBciWDWkt000"},{"name":"Temps qui pete","level":17,"data":"79rEvk1lFNkCu000"},{"name":"Grand Papy","level":17,"data":"191jtwFROTZwu000"},{"name":"Ulatra Violette","level":17,"data":"B9y6TDFy9EYO3000"}]}