{"id":451468,"username":"baboudu86","language":"fr","inscription":"19 août 2008","rank":13027,"points":316,"dinoz":[{"name":"El babou","level":31,"data":"09RYcWze8R6Hb000"},{"name":"Nolofinwe","level":23,"data":"39rYJmU0XnnpJ000"},{"name":"Ploup","level":21,"data":"79Y1EWOwVgqZn000"},{"name":"donkeykong","level":18,"data":"A9YPH29Ngl4Ff000"},{"name":"Portocruz","level":18,"data":"89BcWHAq567uY000"},{"name":"keneda","level":17,"data":"B9SvxsNdFbZ72000"},{"name":"bluestork","level":16,"data":"49yB4fdVcGwN9000"},{"name":"mozaic","level":17,"data":"29F65jUWRCa3p000"},{"name":"unicef","level":16,"data":"09nkuPMMBMT0c000"},{"name":"pterozeu","level":16,"data":"69LVGZsXRgsuf000"},{"name":"pingou","level":17,"data":"19c37gbBVtJuj000"},{"name":"balboa","level":15,"data":"596JhfGYjv1Pm000"},{"name":"Hipo","level":16,"data":"99J353vvBFFwN000"},{"name":"clasius","level":15,"data":"59sMVV6gEtyUX000"},{"name":"Pingou","level":15,"data":"19znuYJLDQPBy000"},{"name":"Diddy","level":15,"data":"A9xMtbFjsJb6g000"},{"name":"Lor","level":15,"data":"59nqDd6wdTBDg000"},{"name":"Ploup","level":15,"data":"29ZkqOtI1FxwC000"}]}