{"id":482533,"username":"Aarn","language":"fr","inscription":"30 août 2008","rank":3582,"points":676,"dinoz":[{"name":"Aarny","level":40,"data":"29HLYkq5GpCkf000"},{"name":"Mila","level":39,"data":"594nIQCg7wahr000"},{"name":"Mini","level":34,"data":"696hwwRweeIFt000"},{"name":"Kayvel","level":34,"data":"191dNP5ttiMTQ000"},{"name":"Mustang","level":39,"data":"89WxcPxDuaOph000"},{"name":"Whisper","level":39,"data":"B9Feg4BKMQG3x000"},{"name":"Gerard","level":39,"data":"2983YKYAnCmlv000"},{"name":"Francis","level":35,"data":"19u1Ah6BJNXMP000"},{"name":"Leader Ingenieur","level":21,"data":"A9d2twMkTZrhb000"},{"name":"Niang","level":36,"data":"59XU9uYnWMEe5000"},{"name":"Diawara","level":33,"data":"19fqvQ8c6eyok000"},{"name":"Valbu","level":33,"data":"89jgmJfD6RC93000"},{"name":"Bernard","level":33,"data":"89ALeQ5k5n7Q2000"},{"name":"Lucho","level":34,"data":"59VhkdeqFZOyD000"},{"name":"Energizer","level":24,"data":"39dH5fJHzVmjm000"},{"name":"Stardust","level":33,"data":"59ihP1CETwCOO000"},{"name":"Willow","level":25,"data":"B9gAXXolJBdH1000"},{"name":"Madmartigan","level":25,"data":"B9hWlzlP7Zx79000"},{"name":"Fistus","level":34,"data":"BAOJHBnkrtEyW000"},{"name":"Cuvette","level":16,"data":"59fahCWkFzx8s000"},{"name":"Quetzalcoatl","level":16,"data":"59M7T4Dd57jHV000"},{"name":"Oeil de Lynx","level":14,"data":"79eq1zT35gQEA000"}]}