{"id":690723,"username":"grafion","language":"fr","inscription":"15 décembre 2008","rank":959,"points":1346,"dinoz":[{"name":"flulufleu","level":31,"data":"29HoPyoOhnQOU000"},{"name":"gragra","level":37,"data":"59xCT6mb83COG000"},{"name":"zougzoug","level":21,"data":"B9nZgY7bH4j1E000"},{"name":"glinglin","level":20,"data":"39FS5AuVnXhMn000"},{"name":"gogoz","level":35,"data":"79I9tEO2zaPWK000"},{"name":"moumou","level":20,"data":"09UXI988qdY8T000"},{"name":"cracrule","level":20,"data":"497cBAJMkCufY000"},{"name":"grabugri","level":39,"data":"E98qrsP0siJlj000"},{"name":"zouglu","level":31,"data":"19pcTUU7aofjg000"},{"name":"vlouvix","level":25,"data":"69gs5KXDgAQrE000"},{"name":"flulaflou","level":31,"data":"29LUpE4s04ou3000"},{"name":"zigzug","level":14,"data":"B9veNEsCrDXFh000"},{"name":"oueuleup","level":32,"data":"A93Zsze0ZIwgd000"},{"name":"zuglou","level":39,"data":"19ZwbzBMaV2aQ000"},{"name":"grifru","level":39,"data":"89oGjliSWhSu7000"},{"name":"graploc","level":29,"data":"992TwospxkhcI000"},{"name":"glogli","level":12,"data":"39Are4ssvmIzB000"},{"name":"crucrule","level":12,"data":"49aToh2WnpSES000"},{"name":"flilaflu","level":12,"data":"294VqGb12AQte000"},{"name":"zeugzig","level":14,"data":"B9ha0HyO9QrYE000"},{"name":"gluglu","level":14,"data":"39Xg9aeUnjfEE000"},{"name":"graglou","level":14,"data":"99XuYmf9iaDCo000"},{"name":"gagaz","level":15,"data":"79lit437NFNZR000"},{"name":"zugzog","level":15,"data":"B9nWWfMkSQYMj000"},{"name":"graplouf","level":18,"data":"99xVyhmKWseJq000"},{"name":"grugru","level":17,"data":"59M0N1flytb7k000"},{"name":"tutuz","level":17,"data":"C9oQXPxkDx3iG000"},{"name":"moumax","level":17,"data":"098fgXmkqIaII000"},{"name":"fliliflu","level":17,"data":"29dGgV2G0agnk000"},{"name":"ouiloup","level":17,"data":"A9J1LB9v1m878000"},{"name":"zogli","level":17,"data":"19DuP228jxa4S000"},{"name":"zigzag","level":39,"data":"BAPmd0jxbu3zG000"},{"name":"grufri","level":17,"data":"893x97Xr3ae3u000"},{"name":"fessor","level":17,"data":"D9x8VwPCWcLmU000"},{"name":"vlivloux","level":17,"data":"69c5Ggq2rwq3x000"},{"name":"cricrule","level":17,"data":"49r8rKouGKEEW000"},{"name":"gluglin","level":17,"data":"39IW440EwDf8T000"},{"name":"grigri","level":17,"data":"59rctyKULx335000"},{"name":"gluglou","level":16,"data":"39liFxbclElFB000"},{"name":"mimoux","level":16,"data":"09vrXbXdFdjcD000"},{"name":"grubigra","level":16,"data":"E9jOFn2DY2tM2000"},{"name":"vleuvlix","level":16,"data":"69pcl4GfTNdkD000"},{"name":"teuteuz","level":16,"data":"C97yQSOH7hXJo000"},{"name":"totoz","level":16,"data":"C96552ZNrviBK000"},{"name":"flalafla","level":15,"data":"29afgVz4RVgqr000"},{"name":"glogla","level":16,"data":"39FmjFFX4QONv000"},{"name":"oualop","level":16,"data":"A9sVKNFH9NRDT000"},{"name":"guguz","level":15,"data":"79bixaqyB7HEQ000"},{"name":"zeugleu","level":16,"data":"19sNMtOgG7gGb000"},{"name":"ouolip","level":16,"data":"A9S0lLMES1KyV000"},{"name":"zugzug","level":16,"data":"B9tc7QsXOzo48000"},{"name":"glougli","level":15,"data":"39paRGia5ZNTH000"},{"name":"mumox","level":16,"data":"09YFViDVNLjgF000"},{"name":"grafrin","level":16,"data":"89aJWKI06akyh000"},{"name":"zaglou","level":16,"data":"19BKm1gE6gGgx000"},{"name":"greugreu","level":17,"data":"59HB5puLuH9eo000"},{"name":"gleugleu","level":15,"data":"39mPadiMGEHNf000"},{"name":"zogzig","level":15,"data":"B9ZkBevfN2l9U000"},{"name":"crucrile","level":16,"data":"493MggvWcKMEc000"},{"name":"orfess","level":16,"data":"D9CLUa2h0vLug000"},{"name":"zagzug","level":15,"data":"B92fnE5xP1ddq000"},{"name":"grufrin","level":15,"data":"89i78FqVDX3o9000"},{"name":"magafesseur","level":24,"data":"E9XKUQ8whndzG000"},{"name":"grogro","level":11,"data":"59VC8nIc7z7ql000"},{"name":"fluliflin","level":10,"data":"29iOswCUo2ozD000"},{"name":"grabigru","level":11,"data":"E9wmnvT1I84q1000"},{"name":"prechand","level":24,"data":"59Lm18gRS5gU8000"},{"name":"vlonvlon","level":11,"data":"69bHCaMmn4UFj000"},{"name":"cracrale","level":11,"data":"49aluh5tX5Fn4000"},{"name":"leagenieur","level":23,"data":"A9mFhEdtXLPOV000"},{"name":"ouinlop","level":11,"data":"A9GqOs2WSDDuf000"}]}