{"id":786645,"username":"rexraptor144","language":"fr","inscription":"07 mars 2009","rank":6879,"points":481,"dinoz":[{"name":"Bergamote","level":32,"data":"B979lTK5HeAOD000"},{"name":"margouya","level":31,"data":"09KpBcPjNPdz6000"},{"name":"rinnegan","level":30,"data":"89JbMzGdaJZ5k000"},{"name":"dark Jak","level":30,"data":"A9J6j8opPKFA0000"},{"name":"leviathan","level":30,"data":"99BCMizIgkAiU000"},{"name":"SCARHINO","level":29,"data":"29ZSJga3CWcwB000"},{"name":"kazekage","level":30,"data":"69hG1sSnF3zjY000"},{"name":"the orange beast","level":28,"data":"19aQawDT3omPu000"},{"name":"tsuchikage","level":28,"data":"59C9UHSF7v07q000"},{"name":"KillerKrab","level":29,"data":"29MNPvm3sYsjN000"},{"name":"kaisencho","level":28,"data":"B9Sf07Tix9yWR000"},{"name":"mizukage","level":28,"data":"79Jbe4h1rMR5O000"},{"name":"kirikirimai","level":29,"data":"39XgEITerfuPO000"},{"name":"Einstein","level":28,"data":"49rlAdytDGa4R000"},{"name":"gizette","level":28,"data":"B96NvMRQQm4d7000"},{"name":"fontaine de plum","level":28,"data":"59xc1a1rD6R5W000"},{"name":"Naimitsu","level":15,"data":"E9dYn3jSU2ryr000"}]}