{"id":1005993,"username":"LastArcAngel","language":"en","inscription":"08 May 2011","rank":15587,"points":76,"dinoz":[{"name":"ThunderClap","level":15,"data":"79pKrFq677RF2000"},{"name":"Preydator","level":12,"data":"99BeHiIQg9ent000"},{"name":"LaoTzu","level":10,"data":"195nPJjBcuZiN000"},{"name":"Pinky","level":8,"data":"37t786culr7Dy000"},{"name":"Baby Monkey","level":7,"data":"A6yZmeB4Nbfs3000"},{"name":"TheBrain","level":6,"data":"75ZNemPyWgk0a000"},{"name":"Hatzegopteryx","level":5,"data":"64PsIudEAVGiL000"},{"name":"Socrates","level":3,"data":"52CHF9QgR5kZn000"},{"name":"Red Lagomorpha","level":2,"data":"81fxoIIagnWmH000"},{"name":"iseeyou","level":7,"data":"B6o6frUuqFsIr000"},{"name":"Propain","level":1,"data":"005WDm0l6sJNi000"}]}