{"id":115103,"username":"Pingtung","language":"en","inscription":"16 April 2009","rank":8439,"points":172,"dinoz":[{"name":"Pingtung","level":18,"data":"B9DAxEWWVCIrL000"},{"name":"Zenwi","level":16,"data":"A9iugdeV9XTML000"},{"name":"Floof","level":15,"data":"797OyuLuXNTyw000"},{"name":"Wall-E","level":14,"data":"39wrhWbl1TFm9000"},{"name":"B-Marsh","level":14,"data":"69VcoBsNEI1q3000"},{"name":"Jewbot","level":13,"data":"99wmUKXNHMOVK000"},{"name":"Pebbles","level":11,"data":"59kVg0iETVFOi000"},{"name":"Bobby","level":12,"data":"69rUTGiXOEfNs000"},{"name":"Walt","level":11,"data":"29TgabQg1EvWi000"},{"name":"Adi","level":10,"data":"69FoDNIcrcQDf000"},{"name":"Caedon","level":9,"data":"B8tSoTJ5UnY11000"},{"name":"Eddie Royal","level":8,"data":"B7V1r7ySmRnav000"},{"name":"Elvis Dumervil","level":7,"data":"86QBCFJPY0O0o000"},{"name":"Champ Bailey","level":7,"data":"76UNipFa5pDzq000"},{"name":"Goofy Goober","level":7,"data":"06fAiQt9y676M000"}]}