{"id":187277,"username":"Laemar","language":"en","inscription":"23 April 2009","rank":8291,"points":175,"dinoz":[{"name":"Portlek","level":22,"data":"19VQF5GXKaNEN000"},{"name":"Hilmi","level":21,"data":"A90MJNgWoryaT000"},{"name":"Hamdi","level":21,"data":"39CRHwN7pJjDc000"},{"name":"Kadir","level":20,"data":"29miCaDB944pY000"},{"name":"Kadri","level":18,"data":"19CgTrr5aH5Bu000"},{"name":"gaya","level":17,"data":"59wvc2p1skOFs000"},{"name":"Kedi","level":17,"data":"B9PgaPeUB6Z6Y000"},{"name":"Prez","level":17,"data":"99udQf7eDb4UJ000"},{"name":"Gus","level":12,"data":"69XorHpdZB15E000"},{"name":"Paspas","level":10,"data":"49Hk9QnMCiusZ000"}]}