{"id":446088,"username":"jhamilla13","language":"en","inscription":"11 June 2009","rank":11133,"points":124,"dinoz":[{"name":"Chickenhead","level":17,"data":"09bWBCHfrefGB000"},{"name":"Stumpy","level":14,"data":"89Px8PKyqDpDw000"},{"name":"Dumbo","level":13,"data":"39mfxAXLCh2LB000"},{"name":"Diddy","level":13,"data":"A97ejCPTRWxNi000"},{"name":"wifer","level":12,"data":"99cvRMHKdGNJo000"},{"name":"Simba","level":11,"data":"B9indQbXJrvEN000"},{"name":"Puff","level":10,"data":"79I7oscAXR5Q8000"},{"name":"Winky","level":9,"data":"28wBwgMAn6u9n000"},{"name":"Bart","level":8,"data":"17zQLrip313j5000"},{"name":"Toopay","level":7,"data":"46eaxbwIwl8W9000"},{"name":"Petry","level":6,"data":"65ApEJiGiAiee000"},{"name":"Spud","level":4,"data":"53vqtK4bDN39i000"}]}