{"id":476029,"username":"Mayp","language":"en","inscription":"18 June 2009","rank":6399,"points":229,"dinoz":[{"name":"Sahara","level":18,"data":"B9axANhUzwerL000"},{"name":"Grizzly","level":16,"data":"A9Bahk0TMW4cZ000"},{"name":"Chiumbo","level":16,"data":"899pYuVPRATd8000"},{"name":"Kaimana","level":15,"data":"99wDczQyUFeur000"},{"name":"Diego","level":15,"data":"09vGjALzWwqde000"},{"name":"Scoop","level":14,"data":"39dOQfcCSgncA000"},{"name":"Spidy","level":13,"data":"69ps1UBM0CKyF000"},{"name":"Oskar","level":13,"data":"49UWYoNxKf08K000"},{"name":"Molly","level":12,"data":"79dFuq0MLESjH000"},{"name":"Trapper","level":12,"data":"19LwPNvLgPvqk000"},{"name":"Nancy","level":12,"data":"29V4DnObjP1ZT000"},{"name":"Banana","level":11,"data":"69VyLWUpUmjFy000"},{"name":"Hummel","level":11,"data":"29vRAG2eDMykZ000"},{"name":"Blue","level":11,"data":"693Uuz6uZW5K4000"},{"name":"Susi","level":11,"data":"99DgBNPKI1YSq000"},{"name":"Igor","level":11,"data":"69beSzu4UEMlW000"},{"name":"Kasper","level":10,"data":"19ShmNPERDFvU000"},{"name":"Mr Rock","level":8,"data":"57eNd6bFyrCpf000"}]}