{"id":522267,"username":"Zimniy","language":"en","inscription":"27 June 2009","rank":13434,"points":96,"dinoz":[{"name":"Nyaka","level":15,"data":"39zjv84xx8Bf1000"},{"name":"Tuchka","level":13,"data":"792GXlFB637tM000"},{"name":"Zver","level":12,"data":"19XURRVfsN56M000"},{"name":"Barbos","level":11,"data":"4950HE9Ki6W1s000"},{"name":"Godzilko","level":10,"data":"89Fds4iy7gmMl000"},{"name":"Koshmarik","level":9,"data":"98BIIvUIfaj0W000"},{"name":"Klyuvik","level":8,"data":"67g5E5XCR5vBs000"},{"name":"Goldy","level":7,"data":"A6vSKM0DEAorK000"},{"name":"Sinyak","level":6,"data":"05F4iMTtVtYFj000"},{"name":"Murrr","level":5,"data":"B4FAv0O3FIBFd000"}]}