{"id":57726,"username":"lunaura","language":"en","inscription":"09 April 2009","rank":5375,"points":267,"dinoz":[{"name":"Furious","level":23,"data":"B9Wv6gVSyP4ZK000"},{"name":"Raincloud","level":20,"data":"79YbGtiqAVOgF000"},{"name":"Lonely","level":21,"data":"89EnWFJqJJdr0000"},{"name":"Scratch","level":19,"data":"B97hjPXn3jPif000"},{"name":"Lordy","level":19,"data":"497zW8yS9iK2z000"},{"name":"Rainbow","level":19,"data":"99lcDwyg9jqu4000"},{"name":"Scorpio","level":17,"data":"29WxPSZHK92Er000"},{"name":"Rocky","level":17,"data":"59mLiAg8RwYpN000"},{"name":"Donkey Kong","level":17,"data":"A943V67BZfpNK000"},{"name":"white Wing","level":17,"data":"692EXh0sCdCcf000"},{"name":"Nessy","level":18,"data":"999rFDFPtMcHE000"},{"name":"TheBat","level":16,"data":"39oPgLUOkp4On000"},{"name":"Lion","level":16,"data":"19kKfq5RkRl5o000"},{"name":"Mister T","level":15,"data":"09UXxsIUpCVGK000"},{"name":"Puenktchen","level":13,"data":"193U2neaPYlA6000"}]}