{"id":630465,"username":"Pangde","language":"en","inscription":"01 August 2009","rank":8148,"points":178,"dinoz":[{"name":"Pangde","level":28,"data":"19FfwCoBcyTPe000"},{"name":"ZhangLiao","level":25,"data":"99b8hwi8djPAO000"},{"name":"Zhuge Liang","level":21,"data":"79zyDOOkHR32e000"},{"name":"Huang Gai","level":22,"data":"099kXBIBmaQNV000"},{"name":"Xiahou Yuan","level":22,"data":"499P5crTKTDgM000"},{"name":"Zhang He","level":20,"data":"89p0ype253xKZ000"},{"name":"Huang Zhong","level":20,"data":"39PAoqlKPRl6W000"},{"name":"Cao Ren","level":20,"data":"59K0TrEmPQaRt000"}]}