{"id":831456,"username":"Maf911","language":"en","inscription":"29 December 2009","rank":8221,"points":176,"dinoz":[{"name":"Glam","level":18,"data":"09hrZ47IkVbSB000"},{"name":"House","level":17,"data":"394ZYTJJEk8m0000"},{"name":"33nes4astya","level":17,"data":"A9WBhnSp0nwst000"},{"name":"Rigiy","level":13,"data":"89ans9bsjFbto000"},{"name":"Rigik","level":12,"data":"49lkbXdWBHl6J000"},{"name":"Myay","level":12,"data":"79K3mBFcmhijt000"},{"name":"Yelloy","level":12,"data":"A9UF3CjVvDx34000"},{"name":"Crybaby","level":11,"data":"A9YaprjlEBhCy000"},{"name":"Zluka","level":11,"data":"19Xqpz44bAqbh000"},{"name":"Hause","level":10,"data":"B9Unix6ouFWWJ000"},{"name":"wkusnij krab","level":10,"data":"294ZcdfPoSsuK000"},{"name":"Luusya","level":8,"data":"976SUUbNrYg12000"},{"name":"Illos","level":7,"data":"26fkD5wrocgca000"},{"name":"Strange","level":6,"data":"15CtQP8kaNiE1000"},{"name":"Red","level":5,"data":"842FeF7rSA2N3000"},{"name":"annown","level":4,"data":"63gvF7mhiRO2o000"},{"name":"white stone","level":3,"data":"52vM7lfzL5Xzo000"}]}