{"id":855125,"username":"alysonne3","language":"en","inscription":"04 February 2010","rank":10047,"points":140,"dinoz":[{"name":"Blink","level":18,"data":"29iBNkgEtQnMU000"},{"name":"Mink","level":14,"data":"09ENzAlaSUPs4000"},{"name":"Lily","level":13,"data":"39CPZLjs87Z8b000"},{"name":"Aint","level":12,"data":"89dM4OvVYh6Ib000"},{"name":"Sars","level":12,"data":"89Gfpo2ydOjyO000"},{"name":"Hart","level":12,"data":"192BCf7gHf6Zi000"},{"name":"Tutu","level":10,"data":"B92yrit97gC6P000"},{"name":"Hippster Faggot","level":9,"data":"98dg9kKLyeycb000"},{"name":"Hippocrates","level":9,"data":"98rVsWnT1yDLU000"},{"name":"Clampus","level":9,"data":"98Zhbr7lNld8P000"},{"name":"Leroux","level":7,"data":"96xi2U5YaMgTN000"},{"name":"Lerouge","level":6,"data":"955eBKGPGZOYU000"},{"name":"Ima","level":4,"data":"93T7Wa7NKOsPo000"},{"name":"Yura","level":3,"data":"929PoQl71mpHs000"},{"name":"Hiza","level":2,"data":"9148cl2A1EMz1000"}]}