{"id":890890,"username":"cr3izyana","language":"en","inscription":"13 April 2010","rank":12764,"points":103,"dinoz":[{"name":"tweak","level":21,"data":"09DWHgZLLcXnk000"},{"name":"Psycho","level":17,"data":"79WJN6vIrkO7a000"},{"name":"SERENITY","level":18,"data":"89dMIXY0mCgvY000"},{"name":"WINGY","level":15,"data":"39tDF1xyMNey4000"},{"name":"ROCKY","level":9,"data":"58gXha8BGYrcH000"},{"name":"GEESY","level":9,"data":"98NsVNeCUGZAa000"},{"name":"PTERRY","level":6,"data":"65qujxYGKMrwe000"},{"name":"BEAVY","level":4,"data":"43AF0QCenYc1Z000"},{"name":"PIGABOO","level":4,"data":"13jaJCks9ppc0000"}]}