{"id":145003,"username":"DAMOMO","language":"es","inscription":"23 abril 2009","rank":7963,"points":322,"dinoz":[{"name":"DAVID_2193","level":29,"data":"09OKg3aAJZOxS000"},{"name":"DAVID-2193","level":24,"data":"09xkDj9ZvTJXF000"},{"name":"DAVID2193","level":21,"data":"09UENnwewtcmr000"},{"name":"DAVID__2193","level":20,"data":"09SzyMFowmUhv000"},{"name":"DAVID--2193","level":20,"data":"19ivGoMxH0ttX000"},{"name":"DAVID---2193","level":20,"data":"A9xA3QntWU48J000"},{"name":"DAVID-_2193","level":18,"data":"19yMPMFo6a7yr000"},{"name":"DAVID--_2193","level":16,"data":"89hdou4AXmV7i000"},{"name":"DAVID-_-2193","level":17,"data":"391Tujf93UMAz000"},{"name":"DAVID_-_2193","level":18,"data":"A9QfbOO0O1izS000"},{"name":"DAVID--_","level":17,"data":"A9QnFrTQe4Xni000"},{"name":"DAVID-__2193","level":17,"data":"39GbloYwyPMI8000"},{"name":"DAVID__-2193","level":16,"data":"B9RK8a2EgwnyV000"},{"name":"DAVID__--2193","level":16,"data":"59JsCKOWPvYha000"},{"name":"DAVID-_-_2193","level":15,"data":"69wwDIfRLC5ob000"},{"name":"DAVID--_2193","level":15,"data":"391ELZ3ZcKCTk000"},{"name":"DAVID__-_2193","level":12,"data":"99xWDJu67YgTT000"},{"name":"DAVID-_-_-2193","level":11,"data":"297N9a05T0pvk000"}]}