{"id":1468637,"username":"estudillo","language":"es","inscription":"27 noviembre 2010","rank":2957,"points":629,"dinoz":[{"name":"Amarillo","level":31,"data":"197UVcyCxmD80000"},{"name":"Blanquito","level":37,"data":"89W1a6z0jDhAS000"},{"name":"Orejillo","level":32,"data":"39CHchWbHdve3000"},{"name":"Bicho","level":34,"data":"291Ix9lT9FLRe000"},{"name":"Copito","level":32,"data":"A9HOSh5Z0b2kB000"},{"name":"Kinton","level":29,"data":"790q8qRyYA5De000"},{"name":"Charmander","level":28,"data":"09TCKtGYPM1se000"},{"name":"Mapachi","level":31,"data":"699gwWWvqOTfG000"},{"name":"Peli","level":29,"data":"B9y0PsvyaI2Og000"},{"name":"Pato","level":36,"data":"99LHEuB7JGh0B000"},{"name":"Melapido","level":29,"data":"595vDjPe1ag55000"},{"name":"Nemo","level":36,"data":"89TvsZvdLWtdM000"},{"name":"Arzapicha","level":27,"data":"A9d0FEzNuQgDF000"},{"name":"Electricisto","level":28,"data":"39D4PrQB8mza3000"},{"name":"Purgui","level":28,"data":"29zIBqQfnUqNt000"},{"name":"Pelinaero","level":28,"data":"49XPECLYo0lYB000"},{"name":"Peluo","level":29,"data":"596xvkxSwzzLA000"},{"name":"Estratocaster","level":27,"data":"79R8KHC3Tfr4W000"},{"name":"Fisherfish","level":27,"data":"89kPI7Jli2WEw000"},{"name":"Pumuki","level":29,"data":"E9Op01b1b82lU000"},{"name":"Cesar","level":22,"data":"H9Xinb9viY3il000"}]}