{"id":1475882,"username":"Cheronio","language":"es","inscription":"05 diciembre 2010","rank":111,"points":3471,"dinoz":[{"name":"el bago","level":51,"data":"A9qkCvZp0x0Va000"},{"name":"el fatal","level":51,"data":"89UlnlfwDUAfy000"},{"name":"el desgraciado","level":51,"data":"09ZLkb8IYhBrS000"},{"name":"peluchon","level":29,"data":"49hUMZuS7VmsI000"},{"name":"Michiru","level":35,"data":"B91KVBbyVjsw8000"},{"name":"fogozo","level":51,"data":"19O04uUBjvxMM000"},{"name":"el sabandija","level":60,"data":"29Kc5ggIwUoAn000"},{"name":"capotero","level":29,"data":"99gnKoafc7EOF000"},{"name":"terozila","level":50,"data":"69w1PdLawiZZY000"},{"name":"eocoso","level":30,"data":"59jRFwHKyVv0N000"},{"name":"roco","level":26,"data":"59nn69gWgy1aC000"},{"name":"locotas","level":26,"data":"89tJ6Xl1Htzts000"},{"name":"el hotero","level":26,"data":"292dkjAUos16Z000"},{"name":"el kchero","level":26,"data":"A9B4qy3akpDGF000"},{"name":"Micoark","level":50,"data":"H90gPSp7sHeys000"},{"name":"Lucario","level":80,"data":"H92yejKJbQgSX000"},{"name":"Kraken","level":80,"data":"F9sN9IAUWbhK8000"},{"name":"anubis","level":80,"data":"BAIf6FUKA1GML000"},{"name":"Yukibuki","level":51,"data":"E9hrKi2ZlZn8M000"},{"name":"AguNaranjon","level":80,"data":"09khDQQwUHl37000"},{"name":"WarMachine","level":50,"data":"I9gvRe210iwAj000"},{"name":"GAAAAAAAAAAA","level":60,"data":"F9K88zBqvFZXJ000"},{"name":"Cactus Cratus","level":49,"data":"1AQED3UUSbkgx000"},{"name":"Hakubi Matata","level":10,"data":"EAkBMfko41o8X000"},{"name":"Pan con quetzu","level":80,"data":"I9unmWdWlP5RI000"},{"name":"Bembom Ja","level":29,"data":"59hqZatAg2BXs000"},{"name":"CompeUnicas","level":26,"data":"89sRTNqT7ASzM000"},{"name":"CompeUnica2","level":26,"data":"79mxNNK1GH9sJ000"},{"name":"Malardo","level":60,"data":"I98lijXocoFi9000"},{"name":"Michirongo","level":27,"data":"B9OmS3UWTvEWd000"},{"name":"CompeUnica3","level":27,"data":"39CjviAHejvqV000"},{"name":"Coneludo","level":26,"data":"49u6lTrUBAiUP000"},{"name":"Negro Mama","level":27,"data":"A95YfZZfEDlyR000"},{"name":"Mamadisimo","level":29,"data":"09uybTgVkkGb5000"},{"name":"Bart Pigmou","level":27,"data":"19qudcSDBmvk9000"},{"name":"Gatitooo","level":27,"data":"B9jbOAp8cWK2v000"},{"name":"Michito","level":60,"data":"B9OY86LnFr61D000"},{"name":"Sailor Orange","level":27,"data":"89zxuHq8u2wJH000"},{"name":"Gato Ladron","level":28,"data":"B9ZdYCCoIu8pQ000"},{"name":"Barba verde","level":27,"data":"59sLlzhPJJUtS000"},{"name":"Consolatroll","level":27,"data":"59BR8atl2UTQp000"},{"name":"Albino","level":27,"data":"3965jVopQfFOW000"},{"name":"Sanguijuela","level":27,"data":"69B6xMoMDgMtj000"},{"name":"Goto CTM","level":27,"data":"B9owSKK8fUYvC000"},{"name":"Vuela Vuelaaaa","level":27,"data":"39V117U0Rm4um000"},{"name":"Garrapata","level":27,"data":"29fTOqcDh94zo000"},{"name":"Cherito","level":27,"data":"29tnSHFtLp9Py000"},{"name":"Cascabel","level":26,"data":"I99Z7lF96TfHm000"},{"name":"Lluvia","level":26,"data":"796Pol3FSNlJK000"},{"name":"Michirito","level":27,"data":"B94FMwHaLOfpJ000"},{"name":"Gato Vegetariano","level":27,"data":"B9rzP6hkiI6Vv000"},{"name":"Gato vegano","level":27,"data":"B98Z4Ld4y5qW6000"},{"name":"Bicho cr7","level":27,"data":"29nOw7eynYrD2000"},{"name":"Guapeton","level":27,"data":"19vbf6Ew5ZOtx000"},{"name":"AwantaDO","level":27,"data":"39kdHiOxe9hrc000"},{"name":"Impaktadeishon","level":27,"data":"59SWGpR7kNOYW000"},{"name":"Ciclope","level":27,"data":"69vjfaqumJDga000"},{"name":"Serruchin","level":27,"data":"69u8VGdfn1MA6000"},{"name":"Es Bellisimo","level":26,"data":"99zriaU50o26G000"},{"name":"planeta","level":27,"data":"39XvJRugs212F000"},{"name":"Gato tigrillo","level":27,"data":"B9EzXkizi6UJz000"},{"name":"comillos sable","level":60,"data":"49dkIrZoaAURg000"},{"name":"Peque","level":27,"data":"39VStFelZCp26000"},{"name":"Pecho Peludo","level":27,"data":"39uq0vVXCUEAR000"},{"name":"Bendiciones","level":27,"data":"59Hm4wbhBKeHk000"},{"name":"Rico","level":27,"data":"593uJpDiZnbaN000"},{"name":"Cheronio","level":80,"data":"J9RvPXzcyY2WE200"},{"name":"No lo se Rip","level":27,"data":"59i19lPYHvSWT000"},{"name":"Pepa","level":27,"data":"59aH6r285SzW4000"},{"name":"Orejitas","level":27,"data":"39Xk3D2MZaAtd000"},{"name":"Trisonte","level":80,"data":"D91Hr59cBVJpU000"},{"name":"Cosito","level":50,"data":"990yJBADIv3F7000"},{"name":"Moe","level":27,"data":"79Nkfo6s8i8K5000"},{"name":"picudo","level":27,"data":"59eAvknwyBVlD000"},{"name":"Colmillin","level":80,"data":"F9rHaXWwDHZP4000"},{"name":"Di Oro","level":60,"data":"3ARn95hcqncF1000"},{"name":"Makako","level":60,"data":"AAuB5dr0nluBD000"},{"name":"Caballero Feris","level":54,"data":"D9WmXCWoFiP47110"},{"name":"Polma","level":70,"data":"C9hmGZfQzLA4X000"},{"name":"Chettos","level":60,"data":"G90NfzjDdro64000"},{"name":"Cresponpo","level":51,"data":"F9nGlwC74EPwT000"},{"name":"Michiritu","level":51,"data":"BAltLVBHDi7Sg000"},{"name":"Lombrisjeta","level":60,"data":"G92qY8O7tNvlf000"},{"name":"Manivelo","level":60,"data":"F9JnXb3UYclEV000"},{"name":"Gilaso","level":60,"data":"F9404j5TKGGrZ000"},{"name":"Divinoxd","level":44,"data":"J9i5rB4MpWiMv200"}]}