{"id":1675467,"username":"apoloradical","language":"es","inscription":"20 octubre 2011","rank":16363,"points":155,"dinoz":[{"name":"eros","level":20,"data":"89eTv4y6jUNJv000"},{"name":"pelos","level":14,"data":"494kxMa6RjB53000"},{"name":"dkk","level":13,"data":"A9tT0iDMyGI02000"},{"name":"draco","level":12,"data":"09frKuzqkW0iy000"},{"name":"dracula","level":12,"data":"39cnx0GUFhrpk000"},{"name":"gaaz","level":10,"data":"79l0Q5B8MMsNy000"},{"name":"dongato","level":10,"data":"B9ohBtxemOxJK000"},{"name":"pdemonio","level":10,"data":"19yauvC0tBwTS000"},{"name":"la garra","level":9,"data":"28qQXvnYXitee000"},{"name":"bubu","level":9,"data":"68TfJOPRSW3gr000"},{"name":"baba","level":9,"data":"98rgqUSNXpmUJ000"},{"name":"poison","level":7,"data":"A6KUxZW1JhrV0000"},{"name":"iguano","level":6,"data":"0587G5g3xT58T000"},{"name":"leelo","level":5,"data":"54xxXBLlk01gP000"},{"name":"goliat","level":3,"data":"523IbNob6USPi000"},{"name":"beby","level":3,"data":"A2oPHZGEjJtEU000"},{"name":"sesei","level":3,"data":"B256LGBvyZ9kK000"}]}