{"id":1932132,"username":"Zozu","language":"es","inscription":"25 diciembre 2015","rank":16789,"points":150,"dinoz":[{"name":"Monito","level":17,"data":"A9h73eaEzIn4t000"},{"name":"Aviador","level":16,"data":"39sPT09h7lHhp000"},{"name":"GUAPITO","level":16,"data":"89opWjrBSjI7p000"},{"name":"Blu","level":15,"data":"09Fhizz6YMwd4000"},{"name":"Aitor Menta","level":14,"data":"79x9qCXy4628e000"},{"name":"Snifo","level":14,"data":"49dMfL440MYLA000"},{"name":"Clit","level":12,"data":"29f3zvLicwu0S000"},{"name":"Robber","level":13,"data":"69sVA2PkjhHa5000"},{"name":"Frabuloso","level":12,"data":"99h3UA0c33UgI000"},{"name":"Anciano","level":11,"data":"19pMopVuGII70000"},{"name":"Lechoso","level":10,"data":"B9cdOtj1AuSaQ000"}]}