{"id":220230,"username":"marcoant","language":"es","inscription":"02 mayo 2009","rank":4363,"points":498,"dinoz":[{"name":"malverde","level":30,"data":"19tUDvVtybj5W000"},{"name":"mercurio","level":29,"data":"09mLyEQywFKDz000"},{"name":"Aurum","level":29,"data":"39YI9v1dihBB2000"},{"name":"yihad","level":29,"data":"A9uDoUul2Redp000"},{"name":"gladiador","level":29,"data":"89rT2vd9EfonG000"},{"name":"t0rm3nta","level":29,"data":"79yOJVcC1eSrr000"},{"name":"marea r0jaa","level":29,"data":"09XYezwGh4Nuk000"},{"name":"m1Au","level":29,"data":"B92jZWL5yX6z7000"},{"name":"pinzaz","level":29,"data":"29jVC8SqdsCnR000"},{"name":"rApUNc3l","level":29,"data":"49HEroZTtWxl0000"},{"name":"chango","level":28,"data":"A9yxO5XMh6ngg000"},{"name":"zikarii0","level":27,"data":"99H83rDfBVB3g000"},{"name":"3zpaRtan0","level":27,"data":"69xlWn0rbio8N000"},{"name":"Fiera","level":27,"data":"B97WaniMOIw5M000"},{"name":"hades","level":27,"data":"19wDX8P55FzpM000"},{"name":"mafia oscura","level":27,"data":"B9pMPchVtit9i000"},{"name":"3zkR1bN0","level":27,"data":"79JuZZxKMNidx000"},{"name":"kukukan","level":17,"data":"E90H00yysjpQb000"}]}