{"id":469629,"username":"kolga2","language":"es","inscription":"02 junio 2009","rank":9445,"points":280,"dinoz":[{"name":"kolgao","level":26,"data":"39jnG1Fsri6H2000"},{"name":"hevyfeo","level":17,"data":"09JYpTh2TMMF2000"},{"name":"simplevapor","level":18,"data":"79WbS2o2WvKv5000"},{"name":"estrellao","level":17,"data":"89vQ93TP6RrCu000"},{"name":"alfombrilla","level":17,"data":"49MjbTKE3ojTk000"},{"name":"Darkside","level":17,"data":"19iid33P6px96000"},{"name":"ercanih","level":17,"data":"A9bQA6TvkK298000"},{"name":"minipimer","level":17,"data":"69BSHL7DiYQNj000"},{"name":"vaporeon","level":17,"data":"B9pe1ZlL6DPIG000"},{"name":"hydra","level":16,"data":"99zFWu669gAS9000"},{"name":"pulga","level":16,"data":"29L6nQ9tp8BB8000"},{"name":"Siri-On","level":16,"data":"89sxeDvclFxFY000"},{"name":"fluidez","level":15,"data":"89wve3KyDJVXg000"},{"name":"enjabonaoH","level":16,"data":"89ygnlp76pRA4000"},{"name":"stuntman","level":15,"data":"09AjO5G06NSGb000"},{"name":"chococrispi","level":15,"data":"89ybCKiOqM4iW000"},{"name":"rockefor","level":4,"data":"53khKEG4VBh8m000"},{"name":"bris1toke","level":4,"data":"73OncJJODfcCF000"}]}