{"id":511411,"username":"jambury","language":"es","inscription":"10 junio 2009","rank":4703,"points":473,"dinoz":[{"name":"Elendil","level":34,"data":"89lc2ZlFgxcpj000"},{"name":"Brom","level":29,"data":"09vM8TGQUEWTy000"},{"name":"Simba","level":29,"data":"A91gHXtANa5bn000"},{"name":"Artorius","level":26,"data":"59qrEceiOoQwf000"},{"name":"Sauron","level":26,"data":"39he5K9tTkJn0000"},{"name":"Hurin","level":26,"data":"89gnuNrfA4qri000"},{"name":"Varden","level":26,"data":"890RKttGqmjM6000"},{"name":"Morgoth","level":25,"data":"69bFYCnBLkZzm000"},{"name":"Abinadav","level":25,"data":"19eflsKitmPUd000"},{"name":"Iluvatar","level":24,"data":"296tQD2GE5Sir000"},{"name":"Baratheon","level":22,"data":"B9sYGRPASCKwu000"},{"name":"Strutter","level":22,"data":"59JVLCYtsr9sd000"},{"name":"Shlomo","level":22,"data":"B9uyuXa37XObO000"},{"name":"Onomaius","level":22,"data":"29o3yldT4VfKa000"},{"name":"Johan","level":22,"data":"B9QxTZAsrSqg2000"},{"name":"Takeo","level":22,"data":"09NOH8M0N6iVz000"},{"name":"Gengar","level":22,"data":"797N0RxwfVTHV000"},{"name":"Raskolnikov","level":22,"data":"19WC3vZ2eVkE8000"},{"name":"Green Arrow","level":12,"data":"E9ClyjTy8049S000"},{"name":"Shimon","level":10,"data":"39qLJA8dxP5i3000"},{"name":"Kurt","level":10,"data":"19YR9opamL9Im000"}]}