{"id":61787,"username":"cheetos11","language":"es","inscription":"01 febrero 2009","rank":5504,"points":425,"dinoz":[{"name":"ehrinom","level":27,"data":"A9dhNVVXCYISA000"},{"name":"rahedeon","level":19,"data":"09YDvSbXj5nAz000"},{"name":"sylph","level":29,"data":"89SR7AimHErUg000"},{"name":"ZiKLoS","level":18,"data":"099oXroHh19mk000"},{"name":"rhonkest","level":22,"data":"39alsByEcbWUJ000"},{"name":"ehrinom","level":20,"data":"59xE6Veu5mlGG000"},{"name":"Teclis","level":21,"data":"A9eEJ7ZFoJLpY000"},{"name":"brutus","level":21,"data":"69aEEaYMiQQDr000"},{"name":"Haiass","level":27,"data":"297SFWJTV6fHE000"},{"name":"kirtash","level":22,"data":"19lCZEp3bqPB4000"},{"name":"Shail","level":21,"data":"B9DyxCiww0aUg000"},{"name":"Fobos","level":18,"data":"89dCs7SGaa6PI000"},{"name":"Dennis","level":19,"data":"29jeasBmWw6tH000"},{"name":"Skrim","level":18,"data":"19vqogV8r3FPX000"},{"name":"Leader","level":19,"data":"A9yfePrvkSoQC000"},{"name":"Rankor","level":19,"data":"59qO06tbrcOLk000"},{"name":"Bloomber","level":17,"data":"B9nK56EqSCIq6000"},{"name":"Forzex","level":18,"data":"59uPISwS7WszF000"},{"name":"Yarael","level":18,"data":"E9xA1UA9OSe6x000"},{"name":"Zephyr","level":17,"data":"E93l2tIbhbkQe000"},{"name":"Flamion","level":15,"data":"E9leQlPRIZAvL000"}]}